<?xml version="1.0" encoding="UTF-8"?>
<mxGraphModel dx="1063" dy="473" grid="1" gridSize="10" guides="1" tooltips="1" connect="1" arrows="1" fold="1" page="1" pageScale="1" pageWidth="11169" pageHeight="11652" background="#ffffff" math="0" shadow="0"><root><mxCell id="0"/><mxCell id="1" parent="0"/><mxCell id="26" style="edgeStyle=orthogonalEdgeStyle;rounded=0;html=1;exitX=0.5;exitY=1;entryX=0.5;entryY=0;jettySize=auto;orthogonalLoop=1;" edge="1" parent="1" source="2" target="10"><mxGeometry relative="1" as="geometry"/></mxCell><mxCell id="27" style="edgeStyle=orthogonalEdgeStyle;rounded=0;html=1;exitX=0.75;exitY=1;jettySize=auto;orthogonalLoop=1;" edge="1" parent="1" source="2" target="11"><mxGeometry relative="1" as="geometry"/></mxCell><mxCell id="39" style="edgeStyle=orthogonalEdgeStyle;rounded=0;html=1;exitX=1;exitY=0.75;entryX=0.5;entryY=0;jettySize=auto;orthogonalLoop=1;" edge="1" parent="1" source="2" target="7"><mxGeometry relative="1" as="geometry"/></mxCell><mxCell id="2" value="Sciences" style="whiteSpace=wrap;html=1;" vertex="1" parent="1"><mxGeometry x="500" y="10" width="120" height="60" as="geometry"/></mxCell><mxCell id="40" style="edgeStyle=orthogonalEdgeStyle;rounded=0;html=1;exitX=0.25;exitY=1;entryX=0.5;entryY=0;jettySize=auto;orthogonalLoop=1;" edge="1" parent="1" source="7" target="15"><mxGeometry relative="1" as="geometry"/></mxCell><mxCell id="41" style="edgeStyle=orthogonalEdgeStyle;rounded=0;html=1;exitX=0.5;exitY=1;entryX=0.5;entryY=0;jettySize=auto;orthogonalLoop=1;" edge="1" parent="1" source="7" target="14"><mxGeometry relative="1" as="geometry"/></mxCell><mxCell id="42" style="edgeStyle=orthogonalEdgeStyle;rounded=0;html=1;exitX=0.75;exitY=1;entryX=0.5;entryY=0;jettySize=auto;orthogonalLoop=1;" edge="1" parent="1" source="7" target="13"><mxGeometry relative="1" as="geometry"/></mxCell><mxCell id="43" style="edgeStyle=orthogonalEdgeStyle;rounded=0;html=1;exitX=1;exitY=0.75;entryX=0.5;entryY=0;jettySize=auto;orthogonalLoop=1;" edge="1" parent="1" source="7" target="8"><mxGeometry relative="1" as="geometry"/></mxCell><mxCell id="7" value="&lt;div&gt;Social Sciences&lt;/div&gt;" style="whiteSpace=wrap;html=1;" vertex="1" parent="1"><mxGeometry x="1340" y="120" width="120" height="60" as="geometry"/></mxCell><mxCell id="8" value="&lt;div&gt;Political Science&lt;/div&gt;" style="whiteSpace=wrap;html=1;" vertex="1" parent="1"><mxGeometry x="1551" y="210" width="120" height="60" as="geometry"/></mxCell><mxCell id="28" style="edgeStyle=orthogonalEdgeStyle;rounded=0;html=1;exitX=0.5;exitY=1;entryX=0.5;entryY=0;jettySize=auto;orthogonalLoop=1;" edge="1" parent="1" source="10" target="21"><mxGeometry relative="1" as="geometry"/></mxCell><mxCell id="29" style="edgeStyle=orthogonalEdgeStyle;rounded=0;html=1;exitX=0.25;exitY=1;entryX=0.5;entryY=0;jettySize=auto;orthogonalLoop=1;" edge="1" parent="1" source="10" target="24"><mxGeometry relative="1" as="geometry"/></mxCell><mxCell id="30" style="edgeStyle=orthogonalEdgeStyle;rounded=0;html=1;exitX=0;exitY=0.75;jettySize=auto;orthogonalLoop=1;" edge="1" parent="1" source="10" target="25"><mxGeometry relative="1" as="geometry"/></mxCell><mxCell id="10" value="&lt;div&gt;Life Sciences&lt;/div&gt;" style="whiteSpace=wrap;html=1;" vertex="1" parent="1"><mxGeometry x="350" y="120" width="120" height="60" as="geometry"/></mxCell><mxCell id="31" style="edgeStyle=orthogonalEdgeStyle;rounded=0;html=1;exitX=0.25;exitY=1;entryX=0.5;entryY=0;jettySize=auto;orthogonalLoop=1;" edge="1" parent="1" source="11" target="20"><mxGeometry relative="1" as="geometry"/></mxCell><mxCell id="35" style="edgeStyle=orthogonalEdgeStyle;rounded=0;html=1;exitX=0.5;exitY=1;entryX=0.5;entryY=0;jettySize=auto;orthogonalLoop=1;" edge="1" parent="1" source="11" target="17"><mxGeometry relative="1" as="geometry"/></mxCell><mxCell id="11" value="&lt;div&gt;Physical Sciences&lt;/div&gt;" style="whiteSpace=wrap;html=1;" vertex="1" parent="1"><mxGeometry x="680" y="115" width="120" height="60" as="geometry"/></mxCell><mxCell id="13" value="Law" style="whiteSpace=wrap;html=1;" vertex="1" parent="1"><mxGeometry x="1410" y="210" width="120" height="60" as="geometry"/></mxCell><mxCell id="14" value="Economics" style="whiteSpace=wrap;html=1;" vertex="1" parent="1"><mxGeometry x="1270" y="210" width="120" height="60" as="geometry"/></mxCell><mxCell id="15" value="&lt;div&gt;Education&lt;/div&gt;" style="whiteSpace=wrap;html=1;" vertex="1" parent="1"><mxGeometry x="1130" y="210" width="120" height="60" as="geometry"/></mxCell><mxCell id="16" value="Computer Science" style="whiteSpace=wrap;html=1;" vertex="1" parent="1"><mxGeometry x="620" y="305" width="120" height="60" as="geometry"/></mxCell><mxCell id="36" style="edgeStyle=orthogonalEdgeStyle;rounded=0;html=1;exitX=0.25;exitY=1;entryX=0.5;entryY=0;jettySize=auto;orthogonalLoop=1;" edge="1" parent="1" source="17" target="16"><mxGeometry relative="1" as="geometry"/></mxCell><mxCell id="37" style="edgeStyle=orthogonalEdgeStyle;rounded=0;html=1;exitX=0.5;exitY=1;jettySize=auto;orthogonalLoop=1;" edge="1" parent="1" source="17" target="19"><mxGeometry relative="1" as="geometry"/></mxCell><mxCell id="38" style="edgeStyle=orthogonalEdgeStyle;rounded=0;html=1;exitX=0.75;exitY=1;jettySize=auto;orthogonalLoop=1;" edge="1" parent="1" source="17" target="18"><mxGeometry relative="1" as="geometry"/></mxCell><mxCell id="17" value="Engineering" style="whiteSpace=wrap;html=1;" vertex="1" parent="1"><mxGeometry x="770" y="205" width="120" height="60" as="geometry"/></mxCell><mxCell id="18" value="&lt;div&gt;Microwaves &amp;amp; Circuits&lt;/div&gt;" style="whiteSpace=wrap;html=1;" vertex="1" parent="1"><mxGeometry x="900" y="305" width="120" height="60" as="geometry"/></mxCell><mxCell id="19" value="&lt;div&gt;Communications&lt;/div&gt;" style="whiteSpace=wrap;html=1;" vertex="1" parent="1"><mxGeometry x="760" y="305" width="120" height="60" as="geometry"/></mxCell><mxCell id="20" value="&lt;div&gt;Mathematics&lt;/div&gt;" style="whiteSpace=wrap;html=1;" vertex="1" parent="1"><mxGeometry x="590" y="205" width="120" height="60" as="geometry"/></mxCell><mxCell id="32" style="edgeStyle=orthogonalEdgeStyle;rounded=0;html=1;exitX=0.5;exitY=1;jettySize=auto;orthogonalLoop=1;" edge="1" parent="1" source="21" target="23"><mxGeometry relative="1" as="geometry"/></mxCell><mxCell id="33" style="edgeStyle=orthogonalEdgeStyle;rounded=0;html=1;exitX=0.75;exitY=1;jettySize=auto;orthogonalLoop=1;" edge="1" parent="1" source="21" target="22"><mxGeometry relative="1" as="geometry"/></mxCell><mxCell id="21" value="&lt;div&gt;Medicine&lt;/div&gt;" style="whiteSpace=wrap;html=1;" vertex="1" parent="1"><mxGeometry x="400" y="210" width="120" height="60" as="geometry"/></mxCell><mxCell id="22" value="&lt;div&gt;Pharmacokinetics&lt;/div&gt;" style="whiteSpace=wrap;html=1;" vertex="1" parent="1"><mxGeometry x="460" y="305" width="120" height="60" as="geometry"/></mxCell><mxCell id="23" value="&lt;div&gt;Sports Medicine&lt;/div&gt;" style="whiteSpace=wrap;html=1;" vertex="1" parent="1"><mxGeometry x="270" y="310" width="120" height="60" as="geometry"/></mxCell><mxCell id="24" value="&lt;div&gt;Neuroscience&lt;/div&gt;" style="whiteSpace=wrap;html=1;" vertex="1" parent="1"><mxGeometry x="230" y="210" width="120" height="60" as="geometry"/></mxCell><mxCell id="25" value="&lt;div&gt;Molecular &amp;amp; Cell Biology&lt;/div&gt;" style="whiteSpace=wrap;html=1;" vertex="1" parent="1"><mxGeometry x="70" y="210" width="120" height="60" as="geometry"/></mxCell></root></mxGraphModel>